[
  {
    "count": 530,
    "date": "2019-12-04"
  },
  {
    "count": 1245,
    "date": "2019-12-05"
  },
  {
    "count": 1319,
    "date": "2019-12-06"
  },
  {
    "count": 1559,
    "date": "2019-12-07"
  },
  {
    "count": 1792,
    "date": "2019-12-08"
  },
  {
    "count": 1477,
    "date": "2019-12-09"
  },
  {
    "count": 1362,
    "date": "2019-12-10"
  },
  {
    "count": 1404,
    "date": "2019-12-11"
  },
  {
    "count": 1448,
    "date": "2019-12-12"
  },
  {
    "count": 1404,
    "date": "2019-12-13"
  },
  {
    "count": 1478,
    "date": "2019-12-14"
  },
  {
    "count": 1644,
    "date": "2019-12-15"
  },
  {
    "count": 1423,
    "date": "2019-12-16"
  },
  {
    "count": 1316,
    "date": "2019-12-17"
  },
  {
    "count": 1623,
    "date": "2019-12-18"
  },
  {
    "count": 1675,
    "date": "2019-12-19"
  },
  {
    "count": 1717,
    "date": "2019-12-20"
  },
  {
    "count": 1894,
    "date": "2019-12-21"
  },
  {
    "count": 2019,
    "date": "2019-12-22"
  },
  {
    "count": 1797,
    "date": "2019-12-23"
  },
  {
    "count": 1565,
    "date": "2019-12-24"
  },
  {
    "count": 1504,
    "date": "2019-12-25"
  },
  {
    "count": 1687,
    "date": "2019-12-26"
  },
  {
    "count": 2011,
    "date": "2019-12-27"
  },
  {
    "count": 2082,
    "date": "2019-12-28"
  },
  {
    "count": 2442,
    "date": "2019-12-29"
  },
  {
    "count": 2261,
    "date": "2019-12-30"
  },
  {
    "count": 1826,
    "date": "2019-12-31"
  },
  {
    "count": 2111,
    "date": "2020-01-01"
  },
  {
    "count": 2368,
    "date": "2020-01-02"
  },
  {
    "count": 2393,
    "date": "2020-01-03"
  },
  {
    "count": 2424,
    "date": "2020-01-04"
  },
  {
    "count": 2610,
    "date": "2020-01-05"
  },
  {
    "count": 1933,
    "date": "2020-01-06"
  },
  {
    "count": 1777,
    "date": "2020-01-07"
  },
  {
    "count": 1732,
    "date": "2020-01-08"
  },
  {
    "count": 2018,
    "date": "2020-01-09"
  },
  {
    "count": 1758,
    "date": "2020-01-10"
  },
  {
    "count": 2384,
    "date": "2020-01-11"
  },
  {
    "count": 2437,
    "date": "2020-01-12"
  },
  {
    "count": 1985,
    "date": "2020-01-13"
  },
  {
    "count": 2002,
    "date": "2020-01-14"
  },
  {
    "count": 2024,
    "date": "2020-01-15"
  },
  {
    "count": 1986,
    "date": "2020-01-16"
  },
  {
    "count": 1942,
    "date": "2020-01-17"
  },
  {
    "count": 2298,
    "date": "2020-01-18"
  },
  {
    "count": 2621,
    "date": "2020-01-19"
  },
  {
    "count": 1935,
    "date": "2020-01-20"
  },
  {
    "count": 1625,
    "date": "2020-01-21"
  },
  {
    "count": 2013,
    "date": "2020-01-22"
  },
  {
    "count": 2210,
    "date": "2020-01-23"
  },
  {
    "count": 7394,
    "date": "2020-01-24"
  },
  {
    "count": 11143,
    "date": "2020-01-25"
  },
  {
    "count": 11673,
    "date": "2020-01-26"
  },
  {
    "count": 9545,
    "date": "2020-01-27"
  },
  {
    "count": 9510,
    "date": "2020-01-28"
  },
  {
    "count": 9342,
    "date": "2020-01-29"
  },
  {
    "count": 9331,
    "date": "2020-01-30"
  },
  {
    "count": 9994,
    "date": "2020-01-31"
  },
  {
    "count": 11399,
    "date": "2020-02-01"
  },
  {
    "count": 12066,
    "date": "2020-02-02"
  },
  {
    "count": 9104,
    "date": "2020-02-03"
  },
  {
    "count": 9216,
    "date": "2020-02-04"
  },
  {
    "count": 9144,
    "date": "2020-02-05"
  },
  {
    "count": 9052,
    "date": "2020-02-06"
  },
  {
    "count": 9647,
    "date": "2020-02-07"
  },
  {
    "count": 11801,
    "date": "2020-02-08"
  },
  {
    "count": 12236,
    "date": "2020-02-09"
  },
  {
    "count": 9886,
    "date": "2020-02-10"
  },
  {
    "count": 9658,
    "date": "2020-02-11"
  },
  {
    "count": 9551,
    "date": "2020-02-12"
  },
  {
    "count": 9301,
    "date": "2020-02-13"
  },
  {
    "count": 9429,
    "date": "2020-02-14"
  },
  {
    "count": 11201,
    "date": "2020-02-15"
  },
  {
    "count": 11764,
    "date": "2020-02-16"
  },
  {
    "count": 10157,
    "date": "2020-02-17"
  },
  {
    "count": 9191,
    "date": "2020-02-18"
  },
  {
    "count": 9212,
    "date": "2020-02-19"
  },
  {
    "count": 9539,
    "date": "2020-02-20"
  },
  {
    "count": 10259,
    "date": "2020-02-21"
  },
  {
    "count": 11501,
    "date": "2020-02-22"
  },
  {
    "count": 12422,
    "date": "2020-02-23"
  },
  {
    "count": 8821,
    "date": "2020-02-24"
  },
  {
    "count": 11189,
    "date": "2020-02-25"
  },
  {
    "count": 9137,
    "date": "2020-02-26"
  },
  {
    "count": 9488,
    "date": "2020-02-27"
  },
  {
    "count": 10430,
    "date": "2020-02-28"
  },
  {
    "count": 12556,
    "date": "2020-02-29"
  },
  {
    "count": 12797,
    "date": "2020-03-01"
  },
  {
    "count": 9773,
    "date": "2020-03-02"
  },
  {
    "count": 9930,
    "date": "2020-03-03"
  },
  {
    "count": 10019,
    "date": "2020-03-04"
  },
  {
    "count": 10017,
    "date": "2020-03-05"
  },
  {
    "count": 10691,
    "date": "2020-03-06"
  },
  {
    "count": 12566,
    "date": "2020-03-07"
  },
  {
    "count": 12991,
    "date": "2020-03-08"
  },
  {
    "count": 10424,
    "date": "2020-03-09"
  },
  {
    "count": 10433,
    "date": "2020-03-10"
  },
  {
    "count": 10182,
    "date": "2020-03-11"
  },
  {
    "count": 10473,
    "date": "2020-03-12"
  },
  {
    "count": 8754,
    "date": "2020-03-13"
  },
  {
    "count": 10043,
    "date": "2020-03-14"
  },
  {
    "count": 13426,
    "date": "2020-03-15"
  },
  {
    "count": 11638,
    "date": "2020-03-16"
  },
  {
    "count": 12278,
    "date": "2020-03-17"
  },
  {
    "count": 11954,
    "date": "2020-03-18"
  },
  {
    "count": 11312,
    "date": "2020-03-19"
  },
  {
    "count": 10865,
    "date": "2020-03-20"
  },
  {
    "count": 11500,
    "date": "2020-03-21"
  },
  {
    "count": 14413,
    "date": "2020-03-22"
  },
  {
    "count": 14013,
    "date": "2020-03-23"
  },
  {
    "count": 13667,
    "date": "2020-03-24"
  },
  {
    "count": 13782,
    "date": "2020-03-25"
  },
  {
    "count": 13545,
    "date": "2020-03-26"
  },
  {
    "count": 13760,
    "date": "2020-03-27"
  },
  {
    "count": 16508,
    "date": "2020-03-28"
  },
  {
    "count": 17442,
    "date": "2020-03-29"
  },
  {
    "count": 13766,
    "date": "2020-03-30"
  },
  {
    "count": 12093,
    "date": "2020-03-31"
  },
  {
    "count": 14327,
    "date": "2020-04-01"
  },
  {
    "count": 14747,
    "date": "2020-04-02"
  },
  {
    "count": 14806,
    "date": "2020-04-03"
  },
  {
    "count": 17440,
    "date": "2020-04-04"
  },
  {
    "count": 17466,
    "date": "2020-04-05"
  },
  {
    "count": 14681,
    "date": "2020-04-06"
  },
  {
    "count": 14541,
    "date": "2020-04-07"
  },
  {
    "count": 15039,
    "date": "2020-04-08"
  },
  {
    "count": 15346,
    "date": "2020-04-09"
  },
  {
    "count": 16778,
    "date": "2020-04-10"
  },
  {
    "count": 17454,
    "date": "2020-04-11"
  },
  {
    "count": 17066,
    "date": "2020-04-12"
  },
  {
    "count": 17126,
    "date": "2020-04-13"
  },
  {
    "count": 14521,
    "date": "2020-04-14"
  },
  {
    "count": 15251,
    "date": "2020-04-15"
  },
  {
    "count": 15144,
    "date": "2020-04-16"
  },
  {
    "count": 15951,
    "date": "2020-04-17"
  },
  {
    "count": 17546,
    "date": "2020-04-18"
  },
  {
    "count": 18449,
    "date": "2020-04-19"
  },
  {
    "count": 15659,
    "date": "2020-04-20"
  },
  {
    "count": 16450,
    "date": "2020-04-21"
  },
  {
    "count": 14654,
    "date": "2020-04-22"
  },
  {
    "count": 15521,
    "date": "2020-04-23"
  },
  {
    "count": 15089,
    "date": "2020-04-24"
  },
  {
    "count": 19009,
    "date": "2020-04-25"
  },
  {
    "count": 19297,
    "date": "2020-04-26"
  },
  {
    "count": 16697,
    "date": "2020-04-27"
  },
  {
    "count": 17200,
    "date": "2020-04-28"
  },
  {
    "count": 17209,
    "date": "2020-04-29"
  },
  {
    "count": 15958,
    "date": "2020-04-30"
  },
  {
    "count": 7783,
    "date": "2020-05-01"
  },
  {
    "count": 8657,
    "date": "2020-05-02"
  },
  {
    "count": 9408,
    "date": "2020-05-03"
  },
  {
    "count": 11274,
    "date": "2020-05-04"
  },
  {
    "count": 11253,
    "date": "2020-05-05"
  },
  {
    "count": 13332,
    "date": "2020-05-06"
  },
  {
    "count": 14271,
    "date": "2020-05-07"
  },
  {
    "count": 12942,
    "date": "2020-05-08"
  },
  {
    "count": 14099,
    "date": "2020-05-09"
  },
  {
    "count": 19383,
    "date": "2020-05-10"
  },
  {
    "count": 17504,
    "date": "2020-05-11"
  },
  {
    "count": 16194,
    "date": "2020-05-12"
  },
  {
    "count": 16294,
    "date": "2020-05-13"
  },
  {
    "count": 18493,
    "date": "2020-05-14"
  },
  {
    "count": 18228,
    "date": "2020-05-15"
  },
  {
    "count": 19833,
    "date": "2020-05-16"
  },
  {
    "count": 19525,
    "date": "2020-05-17"
  },
  {
    "count": 17580,
    "date": "2020-05-18"
  },
  {
    "count": 17925,
    "date": "2020-05-19"
  },
  {
    "count": 16264,
    "date": "2020-05-20"
  },
  {
    "count": 18363,
    "date": "2020-05-21"
  },
  {
    "count": 18409,
    "date": "2020-05-22"
  },
  {
    "count": 19733,
    "date": "2020-05-23"
  },
  {
    "count": 20315,
    "date": "2020-05-24"
  },
  {
    "count": 18250,
    "date": "2020-05-25"
  },
  {
    "count": 17818,
    "date": "2020-05-26"
  },
  {
    "count": 17365,
    "date": "2020-05-27"
  },
  {
    "count": 17833,
    "date": "2020-05-28"
  },
  {
    "count": 18572,
    "date": "2020-05-29"
  },
  {
    "count": 19452,
    "date": "2020-05-30"
  },
  {
    "count": 19795,
    "date": "2020-05-31"
  },
  {
    "count": 18394,
    "date": "2020-06-01"
  },
  {
    "count": 17549,
    "date": "2020-06-02"
  },
  {
    "count": 17634,
    "date": "2020-06-03"
  },
  {
    "count": 17195,
    "date": "2020-06-04"
  },
  {
    "count": 17869,
    "date": "2020-06-05"
  },
  {
    "count": 18197,
    "date": "2020-06-06"
  },
  {
    "count": 18113,
    "date": "2020-06-07"
  },
  {
    "count": 16156,
    "date": "2020-06-08"
  },
  {
    "count": 17040,
    "date": "2020-06-09"
  },
  {
    "count": 17181,
    "date": "2020-06-10"
  },
  {
    "count": 17830,
    "date": "2020-06-11"
  },
  {
    "count": 16888,
    "date": "2020-06-12"
  },
  {
    "count": 18809,
    "date": "2020-06-13"
  },
  {
    "count": 19542,
    "date": "2020-06-14"
  },
  {
    "count": 16791,
    "date": "2020-06-15"
  },
  {
    "count": 16956,
    "date": "2020-06-16"
  },
  {
    "count": 16781,
    "date": "2020-06-17"
  },
  {
    "count": 16195,
    "date": "2020-06-18"
  },
  {
    "count": 16711,
    "date": "2020-06-19"
  },
  {
    "count": 17793,
    "date": "2020-06-20"
  },
  {
    "count": 18226,
    "date": "2020-06-21"
  },
  {
    "count": 15791,
    "date": "2020-06-22"
  },
  {
    "count": 15768,
    "date": "2020-06-23"
  },
  {
    "count": 15634,
    "date": "2020-06-24"
  },
  {
    "count": 15319,
    "date": "2020-06-25"
  },
  {
    "count": 15584,
    "date": "2020-06-26"
  },
  {
    "count": 16903,
    "date": "2020-06-27"
  },
  {
    "count": 17821,
    "date": "2020-06-28"
  },
  {
    "count": 15982,
    "date": "2020-06-29"
  },
  {
    "count": 17232,
    "date": "2020-06-30"
  },
  {
    "count": 17228,
    "date": "2020-07-01"
  },
  {
    "count": 17634,
    "date": "2020-07-02"
  },
  {
    "count": 17645,
    "date": "2020-07-03"
  },
  {
    "count": 18516,
    "date": "2020-07-04"
  },
  {
    "count": 18263,
    "date": "2020-07-05"
  },
  {
    "count": 16467,
    "date": "2020-07-06"
  },
  {
    "count": 15268,
    "date": "2020-07-07"
  },
  {
    "count": 17142,
    "date": "2020-07-08"
  },
  {
    "count": 17626,
    "date": "2020-07-09"
  },
  {
    "count": 17532,
    "date": "2020-07-10"
  },
  {
    "count": 18530,
    "date": "2020-07-11"
  },
  {
    "count": 19292,
    "date": "2020-07-12"
  },
  {
    "count": 16667,
    "date": "2020-07-13"
  },
  {
    "count": 17814,
    "date": "2020-07-14"
  },
  {
    "count": 17506,
    "date": "2020-07-15"
  },
  {
    "count": 17421,
    "date": "2020-07-16"
  },
  {
    "count": 17642,
    "date": "2020-07-17"
  },
  {
    "count": 18687,
    "date": "2020-07-18"
  },
  {
    "count": 19014,
    "date": "2020-07-19"
  },
  {
    "count": 17104,
    "date": "2020-07-20"
  },
  {
    "count": 17319,
    "date": "2020-07-21"
  },
  {
    "count": 17099,
    "date": "2020-07-22"
  },
  {
    "count": 16552,
    "date": "2020-07-23"
  },
  {
    "count": 17113,
    "date": "2020-07-24"
  },
  {
    "count": 17939,
    "date": "2020-07-25"
  },
  {
    "count": 18944,
    "date": "2020-07-26"
  },
  {
    "count": 16750,
    "date": "2020-07-27"
  },
  {
    "count": 17797,
    "date": "2020-07-28"
  },
  {
    "count": 16865,
    "date": "2020-07-29"
  },
  {
    "count": 17167,
    "date": "2020-07-30"
  },
  {
    "count": 16932,
    "date": "2020-07-31"
  },
  {
    "count": 17837,
    "date": "2020-08-01"
  },
  {
    "count": 18600,
    "date": "2020-08-02"
  },
  {
    "count": 16356,
    "date": "2020-08-03"
  },
  {
    "count": 16428,
    "date": "2020-08-04"
  },
  {
    "count": 16066,
    "date": "2020-08-05"
  },
  {
    "count": 15896,
    "date": "2020-08-06"
  },
  {
    "count": 15598,
    "date": "2020-08-07"
  },
  {
    "count": 17071,
    "date": "2020-08-08"
  },
  {
    "count": 17259,
    "date": "2020-08-09"
  },
  {
    "count": 16142,
    "date": "2020-08-10"
  },
  {
    "count": 14736,
    "date": "2020-08-11"
  },
  {
    "count": 16805,
    "date": "2020-08-12"
  },
  {
    "count": 16304,
    "date": "2020-08-13"
  },
  {
    "count": 16368,
    "date": "2020-08-14"
  },
  {
    "count": 17708,
    "date": "2020-08-15"
  },
  {
    "count": 18144,
    "date": "2020-08-16"
  },
  {
    "count": 16552,
    "date": "2020-08-17"
  },
  {
    "count": 16295,
    "date": "2020-08-18"
  },
  {
    "count": 16379,
    "date": "2020-08-19"
  },
  {
    "count": 15401,
    "date": "2020-08-20"
  },
  {
    "count": 15471,
    "date": "2020-08-21"
  },
  {
    "count": 17458,
    "date": "2020-08-22"
  },
  {
    "count": 17540,
    "date": "2020-08-23"
  },
  {
    "count": 16630,
    "date": "2020-08-24"
  },
  {
    "count": 17251,
    "date": "2020-08-25"
  },
  {
    "count": 17426,
    "date": "2020-08-26"
  },
  {
    "count": 17535,
    "date": "2020-08-27"
  },
  {
    "count": 17911,
    "date": "2020-08-28"
  },
  {
    "count": 19821,
    "date": "2020-08-29"
  },
  {
    "count": 19932,
    "date": "2020-08-30"
  },
  {
    "count": 17236,
    "date": "2020-08-31"
  },
  {
    "count": 17241,
    "date": "2020-09-01"
  },
  {
    "count": 16969,
    "date": "2020-09-02"
  },
  {
    "count": 17111,
    "date": "2020-09-03"
  },
  {
    "count": 17462,
    "date": "2020-09-04"
  },
  {
    "count": 19002,
    "date": "2020-09-05"
  },
  {
    "count": 19468,
    "date": "2020-09-06"
  },
  {
    "count": 17420,
    "date": "2020-09-07"
  },
  {
    "count": 16773,
    "date": "2020-09-08"
  },
  {
    "count": 17647,
    "date": "2020-09-09"
  },
  {
    "count": 16984,
    "date": "2020-09-10"
  },
  {
    "count": 17033,
    "date": "2020-09-11"
  },
  {
    "count": 18954,
    "date": "2020-09-12"
  },
  {
    "count": 19274,
    "date": "2020-09-13"
  },
  {
    "count": 16880,
    "date": "2020-09-14"
  },
  {
    "count": 14979,
    "date": "2020-09-15"
  },
  {
    "count": 16891,
    "date": "2020-09-16"
  },
  {
    "count": 16339,
    "date": "2020-09-17"
  },
  {
    "count": 16624,
    "date": "2020-09-18"
  },
  {
    "count": 18706,
    "date": "2020-09-19"
  },
  {
    "count": 19054,
    "date": "2020-09-20"
  },
  {
    "count": 16827,
    "date": "2020-09-21"
  },
  {
    "count": 17198,
    "date": "2020-09-22"
  },
  {
    "count": 16777,
    "date": "2020-09-23"
  },
  {
    "count": 16657,
    "date": "2020-09-24"
  },
  {
    "count": 16536,
    "date": "2020-09-25"
  },
  {
    "count": 18961,
    "date": "2020-09-26"
  },
  {
    "count": 18880,
    "date": "2020-09-27"
  },
  {
    "count": 16360,
    "date": "2020-09-28"
  },
  {
    "count": 16727,
    "date": "2020-09-29"
  },
  {
    "count": 16741,
    "date": "2020-09-30"
  },
  {
    "count": 16546,
    "date": "2020-10-01"
  },
  {
    "count": 16862,
    "date": "2020-10-02"
  },
  {
    "count": 17916,
    "date": "2020-10-03"
  },
  {
    "count": 17690,
    "date": "2020-10-04"
  },
  {
    "count": 15875,
    "date": "2020-10-05"
  },
  {
    "count": 16256,
    "date": "2020-10-06"
  },
  {
    "count": 14578,
    "date": "2020-10-07"
  },
  {
    "count": 17629,
    "date": "2020-10-08"
  },
  {
    "count": 17635,
    "date": "2020-10-09"
  },
  {
    "count": 18426,
    "date": "2020-10-10"
  },
  {
    "count": 18673,
    "date": "2020-10-11"
  },
  {
    "count": 17784,
    "date": "2020-10-12"
  },
  {
    "count": 17238,
    "date": "2020-10-13"
  },
  {
    "count": 17207,
    "date": "2020-10-14"
  },
  {
    "count": 17287,
    "date": "2020-10-15"
  },
  {
    "count": 17437,
    "date": "2020-10-16"
  },
  {
    "count": 18756,
    "date": "2020-10-17"
  },
  {
    "count": 18203,
    "date": "2020-10-18"
  },
  {
    "count": 16713,
    "date": "2020-10-19"
  },
  {
    "count": 17687,
    "date": "2020-10-20"
  },
  {
    "count": 17137,
    "date": "2020-10-21"
  },
  {
    "count": 17814,
    "date": "2020-10-22"
  },
  {
    "count": 18001,
    "date": "2020-10-23"
  },
  {
    "count": 18570,
    "date": "2020-10-24"
  },
  {
    "count": 19239,
    "date": "2020-10-25"
  },
  {
    "count": 17446,
    "date": "2020-10-26"
  },
  {
    "count": 18378,
    "date": "2020-10-27"
  },
  {
    "count": 18349,
    "date": "2020-10-28"
  },
  {
    "count": 18019,
    "date": "2020-10-29"
  },
  {
    "count": 18473,
    "date": "2020-10-30"
  },
  {
    "count": 20069,
    "date": "2020-10-31"
  },
  {
    "count": 20863,
    "date": "2020-11-01"
  },
  {
    "count": 17829,
    "date": "2020-11-02"
  },
  {
    "count": 17853,
    "date": "2020-11-03"
  },
  {
    "count": 16851,
    "date": "2020-11-04"
  },
  {
    "count": 17338,
    "date": "2020-11-05"
  },
  {
    "count": 18259,
    "date": "2020-11-06"
  },
  {
    "count": 20380,
    "date": "2020-11-07"
  },
  {
    "count": 20717,
    "date": "2020-11-08"
  },
  {
    "count": 17947,
    "date": "2020-11-09"
  },
  {
    "count": 18430,
    "date": "2020-11-10"
  },
  {
    "count": 19588,
    "date": "2020-11-11"
  },
  {
    "count": 18236,
    "date": "2020-11-12"
  },
  {
    "count": 18695,
    "date": "2020-11-13"
  },
  {
    "count": 21471,
    "date": "2020-11-14"
  },
  {
    "count": 21514,
    "date": "2020-11-15"
  },
  {
    "count": 18018,
    "date": "2020-11-16"
  },
  {
    "count": 18401,
    "date": "2020-11-17"
  },
  {
    "count": 16425,
    "date": "2020-11-18"
  },
  {
    "count": 17719,
    "date": "2020-11-19"
  },
  {
    "count": 18022,
    "date": "2020-11-20"
  },
  {
    "count": 20324,
    "date": "2020-11-21"
  },
  {
    "count": 20594,
    "date": "2020-11-22"
  },
  {
    "count": 17177,
    "date": "2020-11-23"
  },
  {
    "count": 14863,
    "date": "2020-11-24"
  },
  {
    "count": 18115,
    "date": "2020-11-25"
  },
  {
    "count": 18019,
    "date": "2020-11-26"
  },
  {
    "count": 18124,
    "date": "2020-11-27"
  },
  {
    "count": 20635,
    "date": "2020-11-28"
  },
  {
    "count": 20746,
    "date": "2020-11-29"
  },
  {
    "count": 17307,
    "date": "2020-11-30"
  },
  {
    "count": 17937,
    "date": "2020-12-01"
  },
  {
    "count": 18073,
    "date": "2020-12-02"
  },
  {
    "count": 18275,
    "date": "2020-12-03"
  },
  {
    "count": 18560,
    "date": "2020-12-04"
  },
  {
    "count": 20517,
    "date": "2020-12-05"
  },
  {
    "count": 20494,
    "date": "2020-12-06"
  },
  {
    "count": 18734,
    "date": "2020-12-07"
  },
  {
    "count": 19683,
    "date": "2020-12-08"
  },
  {
    "count": 18730,
    "date": "2020-12-09"
  },
  {
    "count": 17897,
    "date": "2020-12-10"
  },
  {
    "count": 18465,
    "date": "2020-12-11"
  },
  {
    "count": 20491,
    "date": "2020-12-12"
  },
  {
    "count": 20592,
    "date": "2020-12-13"
  },
  {
    "count": 18090,
    "date": "2020-12-14"
  },
  {
    "count": 18475,
    "date": "2020-12-15"
  },
  {
    "count": 18937,
    "date": "2020-12-16"
  },
  {
    "count": 19124,
    "date": "2020-12-17"
  },
  {
    "count": 19246,
    "date": "2020-12-18"
  },
  {
    "count": 20295,
    "date": "2020-12-19"
  },
  {
    "count": 20603,
    "date": "2020-12-20"
  },
  {
    "count": 19843,
    "date": "2020-12-21"
  },
  {
    "count": 19962,
    "date": "2020-12-22"
  },
  {
    "count": 20552,
    "date": "2020-12-23"
  },
  {
    "count": 18244,
    "date": "2020-12-24"
  },
  {
    "count": 17033,
    "date": "2020-12-25"
  },
  {
    "count": 21072,
    "date": "2020-12-26"
  },
  {
    "count": 22979,
    "date": "2020-12-27"
  },
  {
    "count": 22043,
    "date": "2020-12-28"
  },
  {
    "count": 21450,
    "date": "2020-12-29"
  },
  {
    "count": 21514,
    "date": "2020-12-30"
  },
  {
    "count": 19401,
    "date": "2020-12-31"
  },
  {
    "count": 19337,
    "date": "2021-01-01"
  },
  {
    "count": 23710,
    "date": "2021-01-02"
  },
  {
    "count": 23914,
    "date": "2021-01-03"
  },
  {
    "count": 20976,
    "date": "2021-01-04"
  },
  {
    "count": 21176,
    "date": "2021-01-05"
  },
  {
    "count": 21214,
    "date": "2021-01-06"
  },
  {
    "count": 20880,
    "date": "2021-01-07"
  },
  {
    "count": 21406,
    "date": "2021-01-08"
  },
  {
    "count": 23286,
    "date": "2021-01-09"
  },
  {
    "count": 23469,
    "date": "2021-01-10"
  },
  {
    "count": 20455,
    "date": "2021-01-11"
  },
  {
    "count": 18363,
    "date": "2021-01-12"
  },
  {
    "count": 20871,
    "date": "2021-01-13"
  },
  {
    "count": 21209,
    "date": "2021-01-14"
  },
  {
    "count": 21737,
    "date": "2021-01-15"
  },
  {
    "count": 23488,
    "date": "2021-01-16"
  },
  {
    "count": 24065,
    "date": "2021-01-17"
  },
  {
    "count": 21790,
    "date": "2021-01-18"
  },
  {
    "count": 21674,
    "date": "2021-01-19"
  },
  {
    "count": 22174,
    "date": "2021-01-20"
  },
  {
    "count": 22162,
    "date": "2021-01-21"
  },
  {
    "count": 21714,
    "date": "2021-01-22"
  },
  {
    "count": 23735,
    "date": "2021-01-23"
  },
  {
    "count": 23708,
    "date": "2021-01-24"
  },
  {
    "count": 21771,
    "date": "2021-01-25"
  },
  {
    "count": 22056,
    "date": "2021-01-26"
  },
  {
    "count": 21624,
    "date": "2021-01-27"
  },
  {
    "count": 20751,
    "date": "2021-01-28"
  },
  {
    "count": 22172,
    "date": "2021-01-29"
  },
  {
    "count": 25540,
    "date": "2021-01-30"
  },
  {
    "count": 25809,
    "date": "2021-01-31"
  },
  {
    "count": 18508,
    "date": "2021-02-01"
  },
  {
    "count": 21678,
    "date": "2021-02-02"
  },
  {
    "count": 21285,
    "date": "2021-02-03"
  },
  {
    "count": 20932,
    "date": "2021-02-04"
  },
  {
    "count": 21470,
    "date": "2021-02-05"
  },
  {
    "count": 24817,
    "date": "2021-02-06"
  },
  {
    "count": 25598,
    "date": "2021-02-07"
  },
  {
    "count": 20546,
    "date": "2021-02-08"
  },
  {
    "count": 21336,
    "date": "2021-02-09"
  },
  {
    "count": 21662,
    "date": "2021-02-10"
  },
  {
    "count": 21081,
    "date": "2021-02-11"
  },
  {
    "count": 21781,
    "date": "2021-02-12"
  },
  {
    "count": 23926,
    "date": "2021-02-13"
  },
  {
    "count": 23730,
    "date": "2021-02-14"
  },
  {
    "count": 21654,
    "date": "2021-02-15"
  },
  {
    "count": 21605,
    "date": "2021-02-16"
  },
  {
    "count": 20223,
    "date": "2021-02-17"
  },
  {
    "count": 20622,
    "date": "2021-02-18"
  },
  {
    "count": 20106,
    "date": "2021-02-19"
  },
  {
    "count": 22491,
    "date": "2021-02-20"
  },
  {
    "count": 22613,
    "date": "2021-02-21"
  },
  {
    "count": 19536,
    "date": "2021-02-22"
  },
  {
    "count": 20145,
    "date": "2021-02-23"
  },
  {
    "count": 19604,
    "date": "2021-02-24"
  },
  {
    "count": 19261,
    "date": "2021-02-25"
  },
  {
    "count": 19586,
    "date": "2021-02-26"
  },
  {
    "count": 22008,
    "date": "2021-02-27"
  },
  {
    "count": 21872,
    "date": "2021-02-28"
  },
  {
    "count": 18782,
    "date": "2021-03-01"
  },
  {
    "count": 19214,
    "date": "2021-03-02"
  },
  {
    "count": 18961,
    "date": "2021-03-03"
  },
  {
    "count": 19399,
    "date": "2021-03-04"
  },
  {
    "count": 19440,
    "date": "2021-03-05"
  },
  {
    "count": 22096,
    "date": "2021-03-06"
  },
  {
    "count": 22653,
    "date": "2021-03-07"
  },
  {
    "count": 19959,
    "date": "2021-03-08"
  },
  {
    "count": 16882,
    "date": "2021-03-09"
  },
  {
    "count": 20434,
    "date": "2021-03-10"
  },
  {
    "count": 21137,
    "date": "2021-03-11"
  },
  {
    "count": 21860,
    "date": "2021-03-12"
  },
  {
    "count": 25365,
    "date": "2021-03-13"
  },
  {
    "count": 25777,
    "date": "2021-03-14"
  },
  {
    "count": 21228,
    "date": "2021-03-15"
  },
  {
    "count": 21244,
    "date": "2021-03-16"
  },
  {
    "count": 21376,
    "date": "2021-03-17"
  },
  {
    "count": 18645,
    "date": "2021-03-18"
  },
  {
    "count": 19381,
    "date": "2021-03-19"
  },
  {
    "count": 22018,
    "date": "2021-03-20"
  },
  {
    "count": 20803,
    "date": "2021-03-21"
  },
  {
    "count": 21695,
    "date": "2021-03-22"
  },
  {
    "count": 22109,
    "date": "2021-03-23"
  },
  {
    "count": 22135,
    "date": "2021-03-24"
  },
  {
    "count": 21658,
    "date": "2021-03-25"
  },
  {
    "count": 22063,
    "date": "2021-03-26"
  },
  {
    "count": 24819,
    "date": "2021-03-27"
  },
  {
    "count": 25030,
    "date": "2021-03-28"
  },
  {
    "count": 20188,
    "date": "2021-03-29"
  },
  {
    "count": 18198,
    "date": "2021-03-30"
  },
  {
    "count": 21263,
    "date": "2021-03-31"
  },
  {
    "count": 21102,
    "date": "2021-04-01"
  },
  {
    "count": 23320,
    "date": "2021-04-02"
  },
  {
    "count": 23580,
    "date": "2021-04-03"
  },
  {
    "count": 23405,
    "date": "2021-04-04"
  },
  {
    "count": 23368,
    "date": "2021-04-05"
  },
  {
    "count": 21931,
    "date": "2021-04-06"
  },
  {
    "count": 21782,
    "date": "2021-04-07"
  },
  {
    "count": 21970,
    "date": "2021-04-08"
  },
  {
    "count": 21973,
    "date": "2021-04-09"
  },
  {
    "count": 24538,
    "date": "2021-04-10"
  },
  {
    "count": 26452,
    "date": "2021-04-11"
  },
  {
    "count": 21909,
    "date": "2021-04-12"
  },
  {
    "count": 21948,
    "date": "2021-04-13"
  },
  {
    "count": 21179,
    "date": "2021-04-14"
  },
  {
    "count": 21979,
    "date": "2021-04-15"
  },
  {
    "count": 22257,
    "date": "2021-04-16"
  },
  {
    "count": 24569,
    "date": "2021-04-17"
  },
  {
    "count": 22737,
    "date": "2021-04-18"
  },
  {
    "count": 21123,
    "date": "2021-04-19"
  },
  {
    "count": 21801,
    "date": "2021-04-20"
  },
  {
    "count": 22170,
    "date": "2021-04-21"
  },
  {
    "count": 22488,
    "date": "2021-04-22"
  },
  {
    "count": 22875,
    "date": "2021-04-23"
  },
  {
    "count": 24237,
    "date": "2021-04-24"
  },
  {
    "count": 24950,
    "date": "2021-04-25"
  },
  {
    "count": 21844,
    "date": "2021-04-26"
  },
  {
    "count": 19805,
    "date": "2021-04-27"
  },
  {
    "count": 21833,
    "date": "2021-04-28"
  },
  {
    "count": 21773,
    "date": "2021-04-29"
  },
  {
    "count": 22654,
    "date": "2021-04-30"
  },
  {
    "count": 24900,
    "date": "2021-05-01"
  },
  {
    "count": 24006,
    "date": "2021-05-02"
  },
  {
    "count": 20675,
    "date": "2021-05-03"
  },
  {
    "count": 21277,
    "date": "2021-05-04"
  },
  {
    "count": 21162,
    "date": "2021-05-05"
  },
  {
    "count": 21076,
    "date": "2021-05-06"
  },
  {
    "count": 21273,
    "date": "2021-05-07"
  },
  {
    "count": 23435,
    "date": "2021-05-08"
  },
  {
    "count": 22719,
    "date": "2021-05-09"
  },
  {
    "count": 19835,
    "date": "2021-05-10"
  },
  {
    "count": 20800,
    "date": "2021-05-11"
  },
  {
    "count": 20275,
    "date": "2021-05-12"
  },
  {
    "count": 21548,
    "date": "2021-05-13"
  },
  {
    "count": 20603,
    "date": "2021-05-14"
  },
  {
    "count": 22583,
    "date": "2021-05-15"
  },
  {
    "count": 22977,
    "date": "2021-05-16"
  },
  {
    "count": 16428,
    "date": "2021-05-17"
  },
  {
    "count": 20879,
    "date": "2021-05-18"
  },
  {
    "count": 21323,
    "date": "2021-05-19"
  },
  {
    "count": 20475,
    "date": "2021-05-20"
  },
  {
    "count": 21077,
    "date": "2021-05-21"
  },
  {
    "count": 24137,
    "date": "2021-05-22"
  },
  {
    "count": 23826,
    "date": "2021-05-23"
  },
  {
    "count": 22403,
    "date": "2021-05-24"
  },
  {
    "count": 20939,
    "date": "2021-05-25"
  },
  {
    "count": 20855,
    "date": "2021-05-26"
  },
  {
    "count": 20685,
    "date": "2021-05-27"
  },
  {
    "count": 20891,
    "date": "2021-05-28"
  },
  {
    "count": 21762,
    "date": "2021-05-29"
  },
  {
    "count": 22318,
    "date": "2021-05-30"
  },
  {
    "count": 20007,
    "date": "2021-05-31"
  },
  {
    "count": 20016,
    "date": "2021-06-01"
  },
  {
    "count": 17757,
    "date": "2021-06-02"
  },
  {
    "count": 21511,
    "date": "2021-06-03"
  },
  {
    "count": 20740,
    "date": "2021-06-04"
  },
  {
    "count": 22617,
    "date": "2021-06-05"
  },
  {
    "count": 23727,
    "date": "2021-06-06"
  },
  {
    "count": 20034,
    "date": "2021-06-07"
  },
  {
    "count": 19106,
    "date": "2021-06-08"
  },
  {
    "count": 19102,
    "date": "2021-06-09"
  },
  {
    "count": 19345,
    "date": "2021-06-10"
  },
  {
    "count": 19071,
    "date": "2021-06-11"
  },
  {
    "count": 20805,
    "date": "2021-06-12"
  },
  {
    "count": 21374,
    "date": "2021-06-13"
  },
  {
    "count": 18935,
    "date": "2021-06-14"
  },
  {
    "count": 18660,
    "date": "2021-06-15"
  },
  {
    "count": 18408,
    "date": "2021-06-16"
  },
  {
    "count": 18551,
    "date": "2021-06-17"
  },
  {
    "count": 18350,
    "date": "2021-06-18"
  },
  {
    "count": 18417,
    "date": "2021-06-19"
  },
  {
    "count": 19589,
    "date": "2021-06-20"
  },
  {
    "count": 18539,
    "date": "2021-06-21"
  },
  {
    "count": 18730,
    "date": "2021-06-22"
  },
  {
    "count": 18252,
    "date": "2021-06-23"
  },
  {
    "count": 18531,
    "date": "2021-06-24"
  },
  {
    "count": 17754,
    "date": "2021-06-25"
  },
  {
    "count": 19053,
    "date": "2021-06-26"
  },
  {
    "count": 19530,
    "date": "2021-06-27"
  },
  {
    "count": 18068,
    "date": "2021-06-28"
  },
  {
    "count": 14582,
    "date": "2021-06-29"
  },
  {
    "count": 19783,
    "date": "2021-06-30"
  },
  {
    "count": 19854,
    "date": "2021-07-01"
  },
  {
    "count": 18966,
    "date": "2021-07-02"
  },
  {
    "count": 20279,
    "date": "2021-07-03"
  },
  {
    "count": 21768,
    "date": "2021-07-04"
  },
  {
    "count": 19595,
    "date": "2021-07-05"
  },
  {
    "count": 19312,
    "date": "2021-07-06"
  },
  {
    "count": 17572,
    "date": "2021-07-07"
  },
  {
    "count": 18537,
    "date": "2021-07-08"
  },
  {
    "count": 19326,
    "date": "2021-07-09"
  },
  {
    "count": 20858,
    "date": "2021-07-10"
  },
  {
    "count": 19344,
    "date": "2021-07-11"
  },
  {
    "count": 18308,
    "date": "2021-07-12"
  },
  {
    "count": 19183,
    "date": "2021-07-13"
  },
  {
    "count": 18702,
    "date": "2021-07-14"
  },
  {
    "count": 18494,
    "date": "2021-07-15"
  },
  {
    "count": 18890,
    "date": "2021-07-16"
  },
  {
    "count": 20597,
    "date": "2021-07-17"
  },
  {
    "count": 20712,
    "date": "2021-07-18"
  },
  {
    "count": 17969,
    "date": "2021-07-19"
  },
  {
    "count": 18364,
    "date": "2021-07-20"
  },
  {
    "count": 17645,
    "date": "2021-07-21"
  },
  {
    "count": 18081,
    "date": "2021-07-22"
  },
  {
    "count": 17689,
    "date": "2021-07-23"
  },
  {
    "count": 19269,
    "date": "2021-07-24"
  },
  {
    "count": 19419,
    "date": "2021-07-25"
  },
  {
    "count": 17754,
    "date": "2021-07-26"
  },
  {
    "count": 18527,
    "date": "2021-07-27"
  },
  {
    "count": 18232,
    "date": "2021-07-28"
  },
  {
    "count": 17915,
    "date": "2021-07-29"
  },
  {
    "count": 17699,
    "date": "2021-07-30"
  },
  {
    "count": 19539,
    "date": "2021-07-31"
  },
  {
    "count": 19767,
    "date": "2021-08-01"
  },
  {
    "count": 17197,
    "date": "2021-08-02"
  },
  {
    "count": 14781,
    "date": "2021-08-03"
  },
  {
    "count": 17054,
    "date": "2021-08-04"
  },
  {
    "count": 16478,
    "date": "2021-08-05"
  },
  {
    "count": 16711,
    "date": "2021-08-06"
  },
  {
    "count": 17689,
    "date": "2021-08-07"
  },
  {
    "count": 18948,
    "date": "2021-08-08"
  },
  {
    "count": 16457,
    "date": "2021-08-09"
  },
  {
    "count": 16460,
    "date": "2021-08-10"
  },
  {
    "count": 17057,
    "date": "2021-08-11"
  },
  {
    "count": 17319,
    "date": "2021-08-12"
  },
  {
    "count": 17641,
    "date": "2021-08-13"
  },
  {
    "count": 17949,
    "date": "2021-08-14"
  },
  {
    "count": 17776,
    "date": "2021-08-15"
  },
  {
    "count": 17309,
    "date": "2021-08-16"
  },
  {
    "count": 17303,
    "date": "2021-08-17"
  },
  {
    "count": 17527,
    "date": "2021-08-18"
  },
  {
    "count": 17332,
    "date": "2021-08-19"
  },
  {
    "count": 17341,
    "date": "2021-08-20"
  },
  {
    "count": 18764,
    "date": "2021-08-21"
  },
  {
    "count": 18981,
    "date": "2021-08-22"
  },
  {
    "count": 17398,
    "date": "2021-08-23"
  },
  {
    "count": 17876,
    "date": "2021-08-24"
  },
  {
    "count": 18145,
    "date": "2021-08-25"
  },
  {
    "count": 18128,
    "date": "2021-08-26"
  },
  {
    "count": 18975,
    "date": "2021-08-27"
  },
  {
    "count": 20107,
    "date": "2021-08-28"
  },
  {
    "count": 20562,
    "date": "2021-08-29"
  },
  {
    "count": 18402,
    "date": "2021-08-30"
  },
  {
    "count": 15390,
    "date": "2021-08-31"
  },
  {
    "count": 16877,
    "date": "2021-09-01"
  },
  {
    "count": 17519,
    "date": "2021-09-02"
  },
  {
    "count": 18520,
    "date": "2021-09-03"
  },
  {
    "count": 19397,
    "date": "2021-09-04"
  },
  {
    "count": 19657,
    "date": "2021-09-05"
  },
  {
    "count": 18307,
    "date": "2021-09-06"
  },
  {
    "count": 18601,
    "date": "2021-09-07"
  },
  {
    "count": 18373,
    "date": "2021-09-08"
  },
  {
    "count": 18502,
    "date": "2021-09-09"
  },
  {
    "count": 15199,
    "date": "2021-09-10"
  },
  {
    "count": 21759,
    "date": "2021-09-11"
  },
  {
    "count": 21068,
    "date": "2021-09-12"
  },
  {
    "count": 16200,
    "date": "2021-09-13"
  },
  {
    "count": 16768,
    "date": "2021-09-14"
  },
  {
    "count": 17196,
    "date": "2021-09-15"
  },
  {
    "count": 16984,
    "date": "2021-09-16"
  },
  {
    "count": 18835,
    "date": "2021-09-17"
  },
  {
    "count": 17526,
    "date": "2021-09-18"
  },
  {
    "count": 18168,
    "date": "2021-09-19"
  },
  {
    "count": 19077,
    "date": "2021-09-20"
  },
  {
    "count": 20035,
    "date": "2021-09-21"
  },
  {
    "count": 19925,
    "date": "2021-09-22"
  },
  {
    "count": 19541,
    "date": "2021-09-23"
  },
  {
    "count": 20031,
    "date": "2021-09-24"
  },
  {
    "count": 21609,
    "date": "2021-09-25"
  },
  {
    "count": 21315,
    "date": "2021-09-26"
  },
  {
    "count": 18773,
    "date": "2021-09-27"
  },
  {
    "count": 18811,
    "date": "2021-09-28"
  },
  {
    "count": 18510,
    "date": "2021-09-29"
  },
  {
    "count": 18656,
    "date": "2021-09-30"
  },
  {
    "count": 18656,
    "date": "2021-10-01"
  },
  {
    "count": 20520,
    "date": "2021-10-02"
  },
  {
    "count": 20645,
    "date": "2021-10-03"
  },
  {
    "count": 18464,
    "date": "2021-10-04"
  },
  {
    "count": 17950,
    "date": "2021-10-05"
  },
  {
    "count": 18433,
    "date": "2021-10-06"
  },
  {
    "count": 18082,
    "date": "2021-10-07"
  },
  {
    "count": 18264,
    "date": "2021-10-08"
  },
  {
    "count": 19270,
    "date": "2021-10-09"
  },
  {
    "count": 19489,
    "date": "2021-10-10"
  },
  {
    "count": 18617,
    "date": "2021-10-11"
  },
  {
    "count": 18567,
    "date": "2021-10-12"
  },
  {
    "count": 18388,
    "date": "2021-10-13"
  },
  {
    "count": 17703,
    "date": "2021-10-14"
  },
  {
    "count": 17880,
    "date": "2021-10-15"
  },
  {
    "count": 19520,
    "date": "2021-10-16"
  },
  {
    "count": 19402,
    "date": "2021-10-17"
  },
  {
    "count": 16978,
    "date": "2021-10-18"
  },
  {
    "count": 17430,
    "date": "2021-10-19"
  },
  {
    "count": 16052,
    "date": "2021-10-20"
  },
  {
    "count": 18462,
    "date": "2021-10-21"
  },
  {
    "count": 19251,
    "date": "2021-10-22"
  },
  {
    "count": 21277,
    "date": "2021-10-23"
  },
  {
    "count": 20813,
    "date": "2021-10-24"
  },
  {
    "count": 17542,
    "date": "2021-10-25"
  },
  {
    "count": 17649,
    "date": "2021-10-26"
  },
  {
    "count": 17565,
    "date": "2021-10-27"
  },
  {
    "count": 16677,
    "date": "2021-10-28"
  },
  {
    "count": 16286,
    "date": "2021-10-29"
  },
  {
    "count": 17716,
    "date": "2021-10-30"
  },
  {
    "count": 16570,
    "date": "2021-10-31"
  },
  {
    "count": 17071,
    "date": "2021-11-01"
  },
  {
    "count": 16145,
    "date": "2021-11-02"
  },
  {
    "count": 13071,
    "date": "2021-11-03"
  },
  {
    "count": 15655,
    "date": "2021-11-04"
  },
  {
    "count": 16090,
    "date": "2021-11-05"
  },
  {
    "count": 17106,
    "date": "2021-11-06"
  },
  {
    "count": 17417,
    "date": "2021-11-07"
  },
  {
    "count": 14405,
    "date": "2021-11-08"
  },
  {
    "count": 14939,
    "date": "2021-11-09"
  },
  {
    "count": 12382,
    "date": "2021-11-10"
  },
  {
    "count": 15574,
    "date": "2021-11-11"
  },
  {
    "count": 15309,
    "date": "2021-11-12"
  },
  {
    "count": 17146,
    "date": "2021-11-13"
  },
  {
    "count": 16797,
    "date": "2021-11-14"
  },
  {
    "count": 14499,
    "date": "2021-11-15"
  },
  {
    "count": 14127,
    "date": "2021-11-16"
  },
  {
    "count": 14578,
    "date": "2021-11-17"
  },
  {
    "count": 14569,
    "date": "2021-11-18"
  },
  {
    "count": 14755,
    "date": "2021-11-19"
  },
  {
    "count": 16238,
    "date": "2021-11-20"
  },
  {
    "count": 16317,
    "date": "2021-11-21"
  },
  {
    "count": 15101,
    "date": "2021-11-22"
  },
  {
    "count": 15246,
    "date": "2021-11-23"
  },
  {
    "count": 15286,
    "date": "2021-11-24"
  },
  {
    "count": 14447,
    "date": "2021-11-25"
  },
  {
    "count": 14579,
    "date": "2021-11-26"
  },
  {
    "count": 16888,
    "date": "2021-11-27"
  },
  {
    "count": 16748,
    "date": "2021-11-28"
  },
  {
    "count": 15057,
    "date": "2021-11-29"
  },
  {
    "count": 15186,
    "date": "2021-11-30"
  },
  {
    "count": 15021,
    "date": "2021-12-01"
  },
  {
    "count": 14828,
    "date": "2021-12-02"
  },
  {
    "count": 14247,
    "date": "2021-12-03"
  },
  {
    "count": 16385,
    "date": "2021-12-04"
  },
  {
    "count": 16079,
    "date": "2021-12-05"
  },
  {
    "count": 12715,
    "date": "2021-12-06"
  },
  {
    "count": 15329,
    "date": "2021-12-07"
  },
  {
    "count": 15208,
    "date": "2021-12-08"
  },
  {
    "count": 14902,
    "date": "2021-12-09"
  },
  {
    "count": 13471,
    "date": "2021-12-10"
  },
  {
    "count": 15784,
    "date": "2021-12-11"
  },
  {
    "count": 15476,
    "date": "2021-12-12"
  },
  {
    "count": 14575,
    "date": "2021-12-13"
  },
  {
    "count": 15022,
    "date": "2021-12-14"
  },
  {
    "count": 14884,
    "date": "2021-12-15"
  },
  {
    "count": 14454,
    "date": "2021-12-16"
  },
  {
    "count": 14838,
    "date": "2021-12-17"
  },
  {
    "count": 16349,
    "date": "2021-12-18"
  },
  {
    "count": 16786,
    "date": "2021-12-19"
  },
  {
    "count": 14830,
    "date": "2021-12-20"
  },
  {
    "count": 15070,
    "date": "2021-12-21"
  },
  {
    "count": 15081,
    "date": "2021-12-22"
  },
  {
    "count": 15335,
    "date": "2021-12-23"
  },
  {
    "count": 14187,
    "date": "2021-12-24"
  },
  {
    "count": 13163,
    "date": "2021-12-25"
  },
  {
    "count": 15700,
    "date": "2021-12-26"
  },
  {
    "count": 15863,
    "date": "2021-12-27"
  },
  {
    "count": 16134,
    "date": "2021-12-28"
  },
  {
    "count": 16495,
    "date": "2021-12-29"
  },
  {
    "count": 16770,
    "date": "2021-12-30"
  },
  {
    "count": 15001,
    "date": "2021-12-31"
  },
  {
    "count": 14791,
    "date": "2022-01-01"
  },
  {
    "count": 17846,
    "date": "2022-01-02"
  },
  {
    "count": 16277,
    "date": "2022-01-03"
  },
  {
    "count": 16097,
    "date": "2022-01-04"
  },
  {
    "count": 15925,
    "date": "2022-01-05"
  },
  {
    "count": 16151,
    "date": "2022-01-06"
  },
  {
    "count": 16910,
    "date": "2022-01-07"
  },
  {
    "count": 18340,
    "date": "2022-01-08"
  },
  {
    "count": 18193,
    "date": "2022-01-09"
  },
  {
    "count": 15233,
    "date": "2022-01-10"
  },
  {
    "count": 15551,
    "date": "2022-01-11"
  },
  {
    "count": 16133,
    "date": "2022-01-12"
  },
  {
    "count": 16197,
    "date": "2022-01-13"
  },
  {
    "count": 16984,
    "date": "2022-01-14"
  },
  {
    "count": 18579,
    "date": "2022-01-15"
  },
  {
    "count": 19059,
    "date": "2022-01-16"
  },
  {
    "count": 16509,
    "date": "2022-01-17"
  },
  {
    "count": 16649,
    "date": "2022-01-18"
  },
  {
    "count": 16256,
    "date": "2022-01-19"
  },
  {
    "count": 16801,
    "date": "2022-01-20"
  },
  {
    "count": 17157,
    "date": "2022-01-21"
  },
  {
    "count": 19545,
    "date": "2022-01-22"
  },
  {
    "count": 19635,
    "date": "2022-01-23"
  },
  {
    "count": 16545,
    "date": "2022-01-24"
  },
  {
    "count": 17170,
    "date": "2022-01-25"
  },
  {
    "count": 14079,
    "date": "2022-01-26"
  },
  {
    "count": 17312,
    "date": "2022-01-27"
  },
  {
    "count": 17179,
    "date": "2022-01-28"
  },
  {
    "count": 19208,
    "date": "2022-01-29"
  },
  {
    "count": 18304,
    "date": "2022-01-30"
  },
  {
    "count": 15929,
    "date": "2022-01-31"
  },
  {
    "count": 16299,
    "date": "2022-02-01"
  },
  {
    "count": 16318,
    "date": "2022-02-02"
  },
  {
    "count": 16356,
    "date": "2022-02-03"
  },
  {
    "count": 17321,
    "date": "2022-02-04"
  },
  {
    "count": 18412,
    "date": "2022-02-05"
  },
  {
    "count": 18280,
    "date": "2022-02-06"
  },
  {
    "count": 16415,
    "date": "2022-02-07"
  },
  {
    "count": 16426,
    "date": "2022-02-08"
  },
  {
    "count": 16079,
    "date": "2022-02-09"
  },
  {
    "count": 16541,
    "date": "2022-02-10"
  },
  {
    "count": 17555,
    "date": "2022-02-11"
  },
  {
    "count": 19022,
    "date": "2022-02-12"
  },
  {
    "count": 19611,
    "date": "2022-02-13"
  },
  {
    "count": 15140,
    "date": "2022-02-14"
  },
  {
    "count": 15805,
    "date": "2022-02-15"
  },
  {
    "count": 16252,
    "date": "2022-02-16"
  }
]